wkt/__init__.py
wkt-0.1.4.dist-info/licenses/LICENCE
wkt-0.1.4.dist-info/METADATA
wkt-0.1.4.dist-info/WHEEL
wkt-0.1.4.dist-info/top_level.txt
wkt-0.1.4.dist-info/RECORD
