Metadata-Version: 2.4
Name: wkt
Version: 0.1.4
Summary: WKT generator
Author-email: MrPowers <matthewkevinpowers@gmail.com>
Requires-Python: >=3.11
License-File: LICENCE
Dynamic: license-file
